kaixin/__init__.py
kaixin/kaixin.py
kaixin-1.0.1.dist-info/LICENSE
kaixin-1.0.1.dist-info/METADATA
kaixin-1.0.1.dist-info/WHEEL
kaixin-1.0.1.dist-info/top_level.txt
kaixin-1.0.1.dist-info/RECORD
