Metadata-Version: 2.1
Name: kaixin
Version: 1.0.1
Summary: A Python package, a lot of features are integrated.
Home-page: https://github.com/kaixin168sxz/KaixinPackage
Author: SongXinZhe
Author-email: kaixin168KX@163.com
Classifier: Programming Language :: Python :: 3
Classifier: License :: OSI Approved :: MIT License
Classifier: Operating System :: OS Independent
Requires-Python: >=3.8
License-File: LICENSE
